tlbx/__init__.py
tlbx/callable_utils.py
tlbx/cli_utils.py
tlbx/core_utils.py
tlbx/date_utils.py
tlbx/dict_utils.py
tlbx/email_utils.py
tlbx/file_utils.py
tlbx/iterable_utils.py
tlbx/logging_utils.py
tlbx/object_utils.py
tlbx/string_utils.py
tlbx/version.py
tlbx-0.1.22.dist-info/LICENSE
tlbx-0.1.22.dist-info/METADATA
tlbx-0.1.22.dist-info/WHEEL
tlbx-0.1.22.dist-info/top_level.txt
tlbx-0.1.22.dist-info/RECORD
