Metadata-Version: 2.1
Name: tlbx
Version: 0.1.22
Summary: Just some common utilities.
Home-page: https://github.com/totalhack/tlbx
Author: totalhack
Author-email: none@none.com
Maintainer: totalhack
License: MIT
Platform: UNKNOWN
Classifier: Development Status :: 3 - Alpha
Classifier: License :: OSI Approved :: MIT License
Classifier: Programming Language :: Python :: 3
Requires-Python: >=3.6
License-File: LICENSE
Requires-Dist: attrs
Requires-Dist: climax
Requires-Dist: imapclient
Requires-Dist: ordered-set (~=4.1.0)
Requires-Dist: pprintpp
Requires-Dist: python-dateutil
Requires-Dist: requests
Requires-Dist: simplejson
Requires-Dist: sqlparse
Provides-Extra: complete
Requires-Dist: black ; extra == 'complete'
Requires-Dist: pandas (~=1.5.3) ; extra == 'complete'
Requires-Dist: pre-commit ; extra == 'complete'
Requires-Dist: pylint ; extra == 'complete'
Requires-Dist: pytest (==7.1.2) ; extra == 'complete'
Requires-Dist: twine (~=3.1.1) ; extra == 'complete'
Requires-Dist: wheel ; extra == 'complete'
Provides-Extra: dev
Requires-Dist: black ; extra == 'dev'
Requires-Dist: pre-commit ; extra == 'dev'
Requires-Dist: pylint ; extra == 'dev'
Requires-Dist: pytest (==7.1.2) ; extra == 'dev'
Requires-Dist: twine (~=3.1.1) ; extra == 'dev'
Requires-Dist: wheel ; extra == 'dev'
Provides-Extra: pandas
Requires-Dist: pandas (~=1.5.3) ; extra == 'pandas'
